hisia/__init__.py
hisia/hisia.py
hisia/models/.gitkeep
hisia/models/__init__.py
hisia/models/base_model.pkl
hisia/models/data/stops.pkl
hisia/models/helpers.py
hisia/models/lazylogger.py
hisia/models/train_model.py
hisia/visualization/ROC.png
hisia/visualization/ROC_tests.png
hisia-0.3.3.1.dist-info/LICENSE
hisia-0.3.3.1.dist-info/WHEEL
hisia-0.3.3.1.dist-info/METADATA
hisia-0.3.3.1.dist-info/RECORD
