Metadata-Version: 2.1
Name: hisia
Version: 0.3.3.1
Summary: A Danish sentiment analysis using scikit-learn
Home-page: https://github.com/Proteusiq/hisia
License: MIT
Keywords: nlp,machine_learning,danish,sentiment
Author: Prayson W. Daniel
Author-email: praysonwilfred@gmail.com
Requires-Python: >=3.8.11,<4.0.0
Classifier: License :: OSI Approved :: MIT License
Classifier: Programming Language :: Python :: 3
Classifier: Programming Language :: Python :: 3.10
Classifier: Programming Language :: Python :: 3.9
Requires-Dist: dill (==0.3.4)
Requires-Dist: lemmy (>=2.1.0,<3.0.0)
Requires-Dist: matplotlib (>=3.2.1,<4.0.0)
Requires-Dist: pandas (>=1.0.3,<2.0.0)
Requires-Dist: scikit-learn (==1.0.2)
Project-URL: Repository, https://github.com/Proteusiq/hisia
